odoo/addons/stock_quant_package_multi_reference/README.rst
odoo/addons/stock_quant_package_multi_reference/__init__.py
odoo/addons/stock_quant_package_multi_reference/__manifest__.py
odoo/addons/stock_quant_package_multi_reference/hooks.py
odoo/addons/stock_quant_package_multi_reference/i18n/it.po
odoo/addons/stock_quant_package_multi_reference/i18n/stock_quant_package_multi_reference.pot
odoo/addons/stock_quant_package_multi_reference/models/__init__.py
odoo/addons/stock_quant_package_multi_reference/models/stock_quant_package.py
odoo/addons/stock_quant_package_multi_reference/models/stock_quant_package_reference.py
odoo/addons/stock_quant_package_multi_reference/readme/CONTRIBUTORS.rst
odoo/addons/stock_quant_package_multi_reference/readme/DESCRIPTION.rst
odoo/addons/stock_quant_package_multi_reference/readme/USAGE.rst
odoo/addons/stock_quant_package_multi_reference/security/ir.model.access.csv
odoo/addons/stock_quant_package_multi_reference/static/description/icon.png
odoo/addons/stock_quant_package_multi_reference/static/description/index.html
odoo/addons/stock_quant_package_multi_reference/tests/__init__.py
odoo/addons/stock_quant_package_multi_reference/tests/test_stock_quant_package_multi_reference.py
odoo/addons/stock_quant_package_multi_reference/views/stock_quant_package_view.xml
odoo_addon_stock_quant_package_multi_reference-16.0.1.0.1.dist-info/METADATA
odoo_addon_stock_quant_package_multi_reference-16.0.1.0.1.dist-info/WHEEL
odoo_addon_stock_quant_package_multi_reference-16.0.1.0.1.dist-info/top_level.txt
odoo_addon_stock_quant_package_multi_reference-16.0.1.0.1.dist-info/RECORD
